blender_tissue_cartography/__init__.py
blender_tissue_cartography/_modidx.py
blender_tissue_cartography/diffgeo.py
blender_tissue_cartography/harmonic.py
blender_tissue_cartography/interface_pymeshlab.py
blender_tissue_cartography/interface_trimesh.py
blender_tissue_cartography/interpolation.py
blender_tissue_cartography/io.py
blender_tissue_cartography/mesh.py
blender_tissue_cartography/morphsnakes.py
blender_tissue_cartography/registration.py
blender_tissue_cartography/remesh.py
blender_tissue_cartography/remesh_pymeshlab.py
blender_tissue_cartography/rotation.py
blender_tissue_cartography/smoothing.py
blender_tissue_cartography/wrapping.py
blender_tissue_cartography-0.0.5.dist-info/LICENSE
blender_tissue_cartography-0.0.5.dist-info/METADATA
blender_tissue_cartography-0.0.5.dist-info/WHEEL
blender_tissue_cartography-0.0.5.dist-info/entry_points.txt
blender_tissue_cartography-0.0.5.dist-info/top_level.txt
blender_tissue_cartography-0.0.5.dist-info/RECORD
