Metadata-Version: 2.1
Name: blender-tissue-cartography
Version: 0.0.5
Summary: Pipeline for tissue extraction and analysis of surfaces from volumetric mircroscopy data using blender
Home-page: https://github.com/nikolas-claussen/blender-tissue-cartography
Author: Nikolas
Author-email: nclaussen@ucsb.edu
License: Apache Software License 2.0
Keywords: nbdev jupyter notebook python
Classifier: Development Status :: 4 - Beta
Classifier: Intended Audience :: Developers
Classifier: Natural Language :: English
Classifier: Programming Language :: Python :: 3.7
Classifier: Programming Language :: Python :: 3.8
Classifier: Programming Language :: Python :: 3.9
Classifier: Programming Language :: Python :: 3.10
Classifier: License :: OSI Approved :: Apache Software License
Requires-Python: >=3.7
License-File: LICENSE
Requires-Dist: matplotlib
Requires-Dist: numpy
Requires-Dist: scipy
Requires-Dist: scikit-image
Requires-Dist: tifffile
Requires-Dist: h5py
Requires-Dist: jupyter
Requires-Dist: tqdm
Requires-Dist: libigl ==2.6.1
Provides-Extra: dev
Requires-Dist: nbdev ; extra == 'dev'
Requires-Dist: pymeshlab ; extra == 'dev'
Requires-Dist: trimesh ; extra == 'dev'
Requires-Dist: quaternionic ; extra == 'dev'
Requires-Dist: spherical ; extra == 'dev'
